LICENSE
README.md
setup.py
metacontroller/__init__.py
metacontroller.egg-info/PKG-INFO
metacontroller.egg-info/SOURCES.txt
metacontroller.egg-info/dependency_links.txt
metacontroller.egg-info/top_level.txt
metacontroller.egg-info/zip-safe
metacontroller/internal/__init__.py
metacontroller/internal/exceptions.py
metacontroller/internal/interface.py
metacontroller/internal/method_inspector.py
metacontroller/internal/method_invocation.py
metacontroller/internal/namespace.py
metacontroller/internal/classes/__init__.py
metacontroller/internal/classes/_base.py
metacontroller/internal/classes/do.py
metacontroller/internal/classes/do_all.py
metacontroller/internal/classes/do_k.py
metacontroller/internal/classes/do_one.py
test/test_combinations_args_do_all.py
test/test_combinations_args_do_k.py
test/test_combinations_args_do_one.py
test/test_combinations_do_all copy.py
test/test_combinations_do_all.py
test/test_combinations_do_k.py
test/test_combinations_do_one.py
test/test_inspectors.py
test/test_methods.py
test/test_smoke_do.py
test/test_smoke_do_all.py
test/test_smoke_do_k.py
test/test_smoke_do_one.py